examples/.gitignore
examples/example-notebook.ipynb
examples/example-terrier-anserini-pisa.ipynb
examples/example.py
tests/test_error_handling.py
tests/test_integration.py
tests/test_redundant_tracking.py
tests/test_registered_metadata.py
tests/test_registering_files.py
tests/test_tirex_tracker.py
tests/resources/example-git-repositories.zip
tirex_tracker/__init__.py
tirex_tracker/libtirex_tracker.dylib
tirex_tracker/libtirex_tracker.so
tirex_tracker/py.typed
tirex_tracker/pyterrier.py
tirex_tracker/tirex_tracker.dll
tirex_tracker/utils.py
tirex_tracker/_utils/__init__.py
tirex_tracker/_utils/archive.py
tirex_tracker/_utils/constants.py
tirex_tracker/_utils/errorhandling.py
tirex_tracker/_utils/library.py
tirex_tracker/_utils/results.py
tirex_tracker-0.2.20.dist-info/METADATA
tirex_tracker-0.2.20.dist-info/WHEEL
tirex_tracker-0.2.20.dist-info/top_level.txt
tirex_tracker-0.2.20.dist-info/RECORD
