Metadata-Version: 2.4
Name: tirex-tracker
Version: 0.2.20
Summary: Automatic resource and metadata tracking for information retrieval experiments.
Author-email: Maik Fröbe <maik.froebe@uni-jena.de>, Jan Heinrich Merker <heinrich.merker@uni-jena.de>, Tim Hagen <tim.hagen@uni-kassel.de>
Project-URL: Homepage, https://github.com/tira-io/tirex-tracker
Project-URL: Bug Tracker, https://github.com/tira-io/tirex-tracker/issues
Classifier: Programming Language :: Python :: 3
Classifier: Programming Language :: Python :: 3 :: Only
Classifier: Programming Language :: Python :: 3.8
Classifier: Programming Language :: Python :: 3.9
Classifier: Programming Language :: Python :: 3.10
Classifier: Programming Language :: Python :: 3.11
Classifier: Programming Language :: Python :: 3.12
Classifier: Programming Language :: Python :: 3.13
Classifier: Operating System :: OS Independent
Classifier: Intended Audience :: Science/Research
Classifier: Topic :: Scientific/Engineering
Requires-Python: >=3.8
Requires-Dist: typing-extensions~=4.0
Requires-Dist: importlib-metadata~=8.0
Requires-Dist: importlib-resources~=6.0
Requires-Dist: ipython
Requires-Dist: pyyaml~=6.0
Provides-Extra: tests
Requires-Dist: bandit[toml]~=1.7; extra == "tests"
Requires-Dist: mypy~=1.5; extra == "tests"
Requires-Dist: pandas-stubs~=2.0; extra == "tests"
Requires-Dist: pytest~=8.0; extra == "tests"
Requires-Dist: pytest-cov<8.0,>=5.0; extra == "tests"
Requires-Dist: runnb~=1.0; extra == "tests"
Requires-Dist: ruff<0.15,>=0.9; extra == "tests"
Requires-Dist: types-pyyaml~=6.0; extra == "tests"
Requires-Dist: jupyter~=1.1; extra == "tests"
Provides-Extra: docs
Requires-Dist: sphinx~=8.1; extra == "docs"
Requires-Dist: myst-parser>=4; extra == "docs"
Provides-Extra: examples
Requires-Dist: pandas~=2.0; extra == "examples"
Requires-Dist: python-terrier~=0.13.0; python_version <= "3.12" and extra == "examples"
Requires-Dist: pyterrier-anserini~=0.1.3; python_version >= "3.10" and extra == "examples"
Requires-Dist: pyterrier-pisa~=0.3.0; (python_version <= "3.10" and platform_system != "Darwin") and extra == "examples"
Requires-Dist: seaborn~=0.13.2; extra == "examples"
